odoo/addons/mrp_production_show_post_inventory/README.rst
odoo/addons/mrp_production_show_post_inventory/__init__.py
odoo/addons/mrp_production_show_post_inventory/__manifest__.py
odoo/addons/mrp_production_show_post_inventory/i18n/mrp_production_show_post_inventory.pot
odoo/addons/mrp_production_show_post_inventory/i18n/pt_BR.po
odoo/addons/mrp_production_show_post_inventory/readme/CONTRIBUTORS.rst
odoo/addons/mrp_production_show_post_inventory/readme/DESCRIPTION.rst
odoo/addons/mrp_production_show_post_inventory/static/description/icon.png
odoo/addons/mrp_production_show_post_inventory/static/description/index.html
odoo/addons/mrp_production_show_post_inventory/views/mrp_production.xml
odoo12_addon_mrp_production_show_post_inventory-12.0.1.0.2.dist-info/METADATA
odoo12_addon_mrp_production_show_post_inventory-12.0.1.0.2.dist-info/WHEEL
odoo12_addon_mrp_production_show_post_inventory-12.0.1.0.2.dist-info/top_level.txt
odoo12_addon_mrp_production_show_post_inventory-12.0.1.0.2.dist-info/RECORD
